{"\ud83c\uddfa\ud83c\uddf811\u7f8e\u56fd\u897f\u96c6\u7fa4-\u5168\u7f51\u4f18\u5316(hy2)": {"name": "\ud83c\uddfa\ud83c\uddf811\u7f8e\u56fd\u897f\u96c6\u7fa4-\u5168\u7f51\u4f18\u5316(hy2)", "delay_ms": 183.86395, "packet_loss": 0.0, "jitter_ms": 1.275251202292071, "bandwidth_mbps": null, "stability_score": 100.0, "alive": true, "history": [], "last_tested": 1773895451.159631}, "\ud83c\uddfa\ud83c\uddf812\u7f8e\u56fd\u65e7\u91d1\u5c71-\u5168\u7f51\u4f18\u5316(hy2)": {"name": "\ud83c\uddfa\ud83c\uddf812\u7f8e\u56fd\u65e7\u91d1\u5c71-\u5168\u7f51\u4f18\u5316(hy2)", "delay_ms": 183.60505, "packet_loss": 0.0, "jitter_ms": 1.1229741748448303, "bandwidth_mbps": null, "stability_score": 100.0, "alive": true, "history": [], "last_tested": 1773895457.524878}, "\ud83c\uddfa\ud83c\uddf839\u7f8e\u56fd\u534e\u76db\u987f-\u5168\u7f51\u4f18\u5316(hy2)": {"name": "\ud83c\uddfa\ud83c\uddf839\u7f8e\u56fd\u534e\u76db\u987f-\u5168\u7f51\u4f18\u5316(hy2)", "delay_ms": 183.34285, "packet_loss": 0.0, "jitter_ms": 1.7955511769223833, "bandwidth_mbps": null, "stability_score": 100.0, "alive": true, "history": [], "last_tested": 1773895464.378866}, "\ud83c\uddfa\ud83c\uddf829\u7f8e\u56fd\u65e7\u91d1\u5c71-\u5168\u7f51\u4f18\u5316(hy2)": {"name": "\ud83c\uddfa\ud83c\uddf829\u7f8e\u56fd\u65e7\u91d1\u5c71-\u5168\u7f51\u4f18\u5316(hy2)", "delay_ms": 182.43985, "packet_loss": 0.0, "jitter_ms": 1.0424722273215892, "bandwidth_mbps": null, "stability_score": 100.0, "alive": true, "history": [], "last_tested": 1773895470.736854}, "\ud83c\uddef\ud83c\uddf56\u65e5\u672c-\u8054\u901a/\u79fb\u52a8(hy2)": {"name": "\ud83c\uddef\ud83c\uddf56\u65e5\u672c-\u8054\u901a/\u79fb\u52a8(hy2)", "delay_ms": 182.53495, "packet_loss": 0.0, "jitter_ms": 1.1593346310889316, "bandwidth_mbps": null, "stability_score": 100.0, "alive": true, "history": [], "last_tested": 1773895477.294546}, "\ud83c\uddef\ud83c\uddf57\u65e5\u672c-\u8054\u901a/\u79fb\u52a8(hy2)": {"name": "\ud83c\uddef\ud83c\uddf57\u65e5\u672c-\u8054\u901a/\u79fb\u52a8(hy2)", "delay_ms": 184.72785, "packet_loss": 0.0, "jitter_ms": 7.0247166736272595, "bandwidth_mbps": null, "stability_score": 100.0, "alive": true, "history": [], "last_tested": 1773895483.78934}, "\ud83c\uddf0\ud83c\uddf78\u97e9\u56fd\u96c6\u7fa4-\u5168\u7f51\u4f18\u5316(hy2)": {"name": "\ud83c\uddf0\ud83c\uddf78\u97e9\u56fd\u96c6\u7fa4-\u5168\u7f51\u4f18\u5316(hy2)", "delay_ms": 182.5626, "packet_loss": 0.0, "jitter_ms": 1.0116397528140555, "bandwidth_mbps": null, "stability_score": 100.0, "alive": true, "history": [], "last_tested": 1773895491.051614}, "\ud83c\uddf0\ud83c\uddf79\u97e9\u56fd\u96c6\u7fa4-\u5168\u7f51\u4f18\u5316(hy2)": {"name": "\ud83c\uddf0\ud83c\uddf79\u97e9\u56fd\u96c6\u7fa4-\u5168\u7f51\u4f18\u5316(hy2)", "delay_ms": 183.7609, "packet_loss": 0.0, "jitter_ms": 1.7309948432529854, "bandwidth_mbps": null, "stability_score": 100.0, "alive": true, "history": [], "last_tested": 1773895497.581883}, "\ud83c\uddf0\ud83c\uddf725\u97e9\u56fd\u96c6\u7fa4-\u5168\u7f51\u4f18\u5316(hy2)": {"name": "\ud83c\uddf0\ud83c\uddf725\u97e9\u56fd\u96c6\u7fa4-\u5168\u7f51\u4f18\u5316(hy2)", "delay_ms": 183.11955, "packet_loss": 0.0, "jitter_ms": 0.8975755927702376, "bandwidth_mbps": null, "stability_score": 100.0, "alive": true, "history": [], "last_tested": 1773895504.3273401}, "\ud83c\udde6\ud83c\uddea13\u8fea\u62dc-\u5168\u7f51\u4f18\u5316(hy2)": {"name": "\ud83c\udde6\ud83c\uddea13\u8fea\u62dc-\u5168\u7f51\u4f18\u5316(hy2)", "delay_ms": 182.91140000000001, "packet_loss": 0.0, "jitter_ms": 0.5438510244930174, "bandwidth_mbps": null, "stability_score": 100.0, "alive": true, "history": [], "last_tested": 1773895510.848346}, "\ud83c\uddf8\ud83c\uddec15\u65b0\u52a0\u5761-\u5168\u7f51\u4f18\u5316(hy2)": {"name": "\ud83c\uddf8\ud83c\uddec15\u65b0\u52a0\u5761-\u5168\u7f51\u4f18\u5316(hy2)", "delay_ms": 183.4514, "packet_loss": 0.0, "jitter_ms": 1.2902742833660557, "bandwidth_mbps": null, "stability_score": 100.0, "alive": true, "history": [], "last_tested": 1773895517.691408}, "\ud83c\uddf8\ud83c\uddec24\u65b0\u52a0\u5761-\u8054\u901a/\u79fb\u52a8(hy2)": {"name": "\ud83c\uddf8\ud83c\uddec24\u65b0\u52a0\u5761-\u8054\u901a/\u79fb\u52a8(hy2)", "delay_ms": 184.94205, "packet_loss": 0.0, "jitter_ms": 2.858943335809303, "bandwidth_mbps": null, "stability_score": 100.0, "alive": true, "history": [], "last_tested": 1773895524.0709262}, "\ud83c\uddee\ud83c\uddf314\u5370\u5ea6-\u79fb\u52a8/\u5357\u65b9\u8054\u901a(hy2)": {"name": "\ud83c\uddee\ud83c\uddf314\u5370\u5ea6-\u79fb\u52a8/\u5357\u65b9\u8054\u901a(hy2)", "delay_ms": 183.25115, "packet_loss": 0.0, "jitter_ms": 1.344289218372142, "bandwidth_mbps": null, "stability_score": 100.0, "alive": true, "history": [], "last_tested": 1773895530.714905}, "\ud83c\udde9\ud83c\uddea16\u5fb7\u56fd-\u7535\u4fe1/\u8054\u901a(hy2)": {"name": "\ud83c\udde9\ud83c\uddea16\u5fb7\u56fd-\u7535\u4fe1/\u8054\u901a(hy2)", "delay_ms": 182.93215, "packet_loss": 0.0, "jitter_ms": 0.9350266686317754, "bandwidth_mbps": null, "stability_score": 100.0, "alive": true, "history": [], "last_tested": 1773895537.066921}, "\ud83c\uddec\ud83c\udde717\u82f1\u56fd-\u5168\u7f51\u4f18\u5316(hy2)": {"name": "\ud83c\uddec\ud83c\udde717\u82f1\u56fd-\u5168\u7f51\u4f18\u5316(hy2)", "delay_ms": 184.2175, "packet_loss": 0.0, "jitter_ms": 2.2119434774352658, "bandwidth_mbps": null, "stability_score": 100.0, "alive": true, "history": [], "last_tested": 1773895543.408051}, "\ud83c\udde8\ud83c\udde618\u52a0\u62ff\u5927-\u5168\u7f51\u4f18\u5316(hy2)": {"name": "\ud83c\udde8\ud83c\udde618\u52a0\u62ff\u5927-\u5168\u7f51\u4f18\u5316(hy2)", "delay_ms": 183.7061, "packet_loss": 0.0, "jitter_ms": 1.133531412514842, "bandwidth_mbps": null, "stability_score": 100.0, "alive": true, "history": [], "last_tested": 1773895549.862634}, "\ud83c\udde6\ud83c\uddfa19\u6fb3\u6d32-\u79fb\u52a8\u4f18\u5316(hy2)": {"name": "\ud83c\udde6\ud83c\uddfa19\u6fb3\u6d32-\u79fb\u52a8\u4f18\u5316(hy2)", "delay_ms": 188.43145, "packet_loss": 0.0, "jitter_ms": 3.771526418266776, "bandwidth_mbps": null, "stability_score": 100.0, "alive": true, "history": [], "last_tested": 1773895556.389245}, "\ud83c\udde7\ud83c\uddf720\u5df4\u897f-\u5168\u7f51\u4f18\u5316(hy2)": {"name": "\ud83c\udde7\ud83c\uddf720\u5df4\u897f-\u5168\u7f51\u4f18\u5316(hy2)", "delay_ms": 183.49145, "packet_loss": 0.0, "jitter_ms": 1.2079208528881773, "bandwidth_mbps": null, "stability_score": 100.0, "alive": true, "history": [], "last_tested": 1773895562.928643}, "\ud83c\udde8\ud83c\uddf121\u667a\u5229-\u5168\u7f51\u4f18\u5316(hy2)": {"name": "\ud83c\udde8\ud83c\uddf121\u667a\u5229-\u5168\u7f51\u4f18\u5316(hy2)", "delay_ms": 182.15019999999998, "packet_loss": 0.0, "jitter_ms": 0.5706619978494064, "bandwidth_mbps": null, "stability_score": 100.0, "alive": true, "history": [], "last_tested": 1773895569.36405}, "\ud83c\uddeb\ud83c\uddf723\u6cd5\u56fd-\u5168\u7f51\u4f18\u5316(hy2)": {"name": "\ud83c\uddeb\ud83c\uddf723\u6cd5\u56fd-\u5168\u7f51\u4f18\u5316(hy2)", "delay_ms": 183.3424, "packet_loss": 0.0, "jitter_ms": 0.971961846771233, "bandwidth_mbps": null, "stability_score": 100.0, "alive": true, "history": [], "last_tested": 1773895575.801907}, "\ud83c\uddf2\ud83c\uddfd27\u58a8\u897f\u54e5-\u5168\u7f51\u4f18\u5316(hy2)": {"name": "\ud83c\uddf2\ud83c\uddfd27\u58a8\u897f\u54e5-\u5168\u7f51\u4f18\u5316(hy2)", "delay_ms": 183.575, "packet_loss": 0.0, "jitter_ms": 1.6749307291253617, "bandwidth_mbps": null, "stability_score": 100.0, "alive": true, "history": [], "last_tested": 1773895582.197133}, "\ud83c\uddf3\ud83c\uddf128\u8377\u5170-\u5168\u7f51\u4f18\u5316(hy2)": {"name": "\ud83c\uddf3\ud83c\uddf128\u8377\u5170-\u5168\u7f51\u4f18\u5316(hy2)", "delay_ms": 183.3849, "packet_loss": 0.0, "jitter_ms": 1.0944663636003753, "bandwidth_mbps": null, "stability_score": 100.0, "alive": true, "history": [], "last_tested": 1773895588.62382}, "\ud83c\uddea\ud83c\uddf831\u897f\u73ed\u7259-\u5168\u7f51\u4f18\u5316(hy2)": {"name": "\ud83c\uddea\ud83c\uddf831\u897f\u73ed\u7259-\u5168\u7f51\u4f18\u5316(hy2)", "delay_ms": 183.2103, "packet_loss": 0.0, "jitter_ms": 1.5020421572330331, "bandwidth_mbps": null, "stability_score": 100.0, "alive": true, "history": [], "last_tested": 1773895595.25557}, "\ud83c\uddee\ud83c\uddf130\u4ee5\u8272\u5217-\u5168\u7f51\u4f18\u5316(hy2)": {"name": "\ud83c\uddee\ud83c\uddf130\u4ee5\u8272\u5217-\u5168\u7f51\u4f18\u5316(hy2)", "delay_ms": 184.17335, "packet_loss": 0.0, "jitter_ms": 1.205593336123448, "bandwidth_mbps": null, "stability_score": 100.0, "alive": true, "history": [], "last_tested": 1773895601.836052}, "\ud83c\uddff\ud83c\udde643\u5357\u975e-\u7ea6\u7ff0\u5185\u65af\u5821(hy2)": {"name": "\ud83c\uddff\ud83c\udde643\u5357\u975e-\u7ea6\u7ff0\u5185\u65af\u5821(hy2)", "delay_ms": 183.95420000000001, "packet_loss": 0.0, "jitter_ms": 2.1013639580545127, "bandwidth_mbps": null, "stability_score": 100.0, "alive": true, "history": [], "last_tested": 1773895608.2320268}, "\ud83c\uddea\ud83c\uddf8\ud83c\udde8\ud83c\udded41\u745e\u58eb-\u5168\u7f51\u4f18\u5316(hy2)": {"name": "\ud83c\uddea\ud83c\uddf8\ud83c\udde8\ud83c\udded41\u745e\u58eb-\u5168\u7f51\u4f18\u5316(hy2)", "delay_ms": 183.63945, "packet_loss": 0.0, "jitter_ms": 1.2097229119447983, "bandwidth_mbps": null, "stability_score": 100.0, "alive": true, "history": [], "last_tested": 1773895614.631685}, "4\u53f0\u6e7e-\u8054\u901a\u4f18\u5316(hy2)": {"name": "4\u53f0\u6e7e-\u8054\u901a\u4f18\u5316(hy2)", "delay_ms": 111, "packet_loss": 0.0, "jitter_ms": 1.5457591355910387, "bandwidth_mbps": null, "stability_score": 100.0, "alive": true, "history": [], "last_tested": 1773895620.897321}, "5\u53f0\u6e7e-\u8054\u901a\u4f18\u5316(hy2)": {"name": "5\u53f0\u6e7e-\u8054\u901a\u4f18\u5316(hy2)", "delay_ms": 183.841, "packet_loss": 0.0, "jitter_ms": 1.4704683464443329, "bandwidth_mbps": null, "stability_score": 100.0, "alive": true, "history": [], "last_tested": 1773895627.303336}}